{"nodes": [{"id": "d_my_head_folders_my_desktop_agentic_loop_graph_tmp_mem0_server_models_py", "label": "models.py", "file_type": "code", "source_file": ".tmp_mem0/server/models.py", "source_location": "L1"}, {"id": "server_models_utcnow", "label": "_utcnow()", "file_type": "code", "source_file": ".tmp_mem0/server/models.py", "source_location": "L10"}, {"id": "datetime", "label": "datetime", "file_type": "code", "source_file": ".tmp_mem0/server/models.py", "source_location": "L10"}, {"id": "server_models_new_uuid", "label": "_new_uuid()", "file_type": "code", "source_file": ".tmp_mem0/server/models.py", "source_location": "L14"}, {"id": "uuid", "label": "UUID", "file_type": "code", "source_file": ".tmp_mem0/server/models.py", "source_location": "L14"}, {"id": "server_models_user", "label": "User", "file_type": "code", "source_file": ".tmp_mem0/server/models.py", "source_location": "L18"}, {"id": "base", "label": "Base", "file_type": "code", "source_file": "", "source_location": ""}, {"id": "server_models_apikey", "label": "APIKey", "file_type": "code", "source_file": ".tmp_mem0/server/models.py", "source_location": "L30"}, {"id": "server_models_requestlog", "label": "RequestLog", "file_type": "code", "source_file": ".tmp_mem0/server/models.py", "source_location": "L43"}, {"id": "server_models_refreshtokenjti", "label": "RefreshTokenJti", "file_type": "code", "source_file": ".tmp_mem0/server/models.py", "source_location": "L55"}, {"id": "server_models_settings", "label": "Settings", "file_type": "code", "source_file": ".tmp_mem0/server/models.py", "source_location": "L65"}], "edges": [{"source": "d_my_head_folders_my_desktop_agentic_loop_graph_tmp_mem0_server_models_py", "target": "uuid", "relation": "imports", "context": "import", "confidence": "EXTRACTED", "source_file": ".tmp_mem0/server/models.py", "source_location": "L1", "weight": 1.0}, {"source": "d_my_head_folders_my_desktop_agentic_loop_graph_tmp_mem0_server_models_py", "target": "datetime", "relation": "imports_from", "context": "import", "confidence": "EXTRACTED", "source_file": ".tmp_mem0/server/models.py", "source_location": "L2", "weight": 1.0}, {"source": "d_my_head_folders_my_desktop_agentic_loop_graph_tmp_mem0_server_models_py", "target": "sqlalchemy", "relation": "imports_from", "context": "import", "confidence": "EXTRACTED", "source_file": ".tmp_mem0/server/models.py", "source_location": "L4", "weight": 1.0}, {"source": "d_my_head_folders_my_desktop_agentic_loop_graph_tmp_mem0_server_models_py", "target": "sqlalchemy_orm", "relation": "imports_from", "context": "import", "confidence": "EXTRACTED", "source_file": ".tmp_mem0/server/models.py", "source_location": "L5", "weight": 1.0}, {"source": "d_my_head_folders_my_desktop_agentic_loop_graph_tmp_mem0_server_models_py", "target": "db", "relation": "imports_from", "context": "import", "confidence": "EXTRACTED", "source_file": ".tmp_mem0/server/models.py", "source_location": "L7", "weight": 1.0}, {"source": "d_my_head_folders_my_desktop_agentic_loop_graph_tmp_mem0_server_models_py", "target": "server_models_utcnow", "relation": "contains", "confidence": "EXTRACTED", "source_file": ".tmp_mem0/server/models.py", "source_location": "L10", "weight": 1.0}, {"source": "server_models_utcnow", "target": "datetime", "relation": "references", "context": "return_type", "confidence": "EXTRACTED", "source_file": ".tmp_mem0/server/models.py", "source_location": "L10", "weight": 1.0}, {"source": "d_my_head_folders_my_desktop_agentic_loop_graph_tmp_mem0_server_models_py", "target": "server_models_new_uuid", "relation": "contains", "confidence": "EXTRACTED", "source_file": ".tmp_mem0/server/models.py", "source_location": "L14", "weight": 1.0}, {"source": "server_models_new_uuid", "target": "uuid", "relation": "references", "context": "return_type", "confidence": "EXTRACTED", "source_file": ".tmp_mem0/server/models.py", "source_location": "L14", "weight": 1.0}, {"source": "d_my_head_folders_my_desktop_agentic_loop_graph_tmp_mem0_server_models_py", "target": "server_models_user", "relation": "contains", "confidence": "EXTRACTED", "source_file": ".tmp_mem0/server/models.py", "source_location": "L18", "weight": 1.0}, {"source": "server_models_user", "target": "base", "relation": "inherits", "confidence": "EXTRACTED", "source_file": ".tmp_mem0/server/models.py", "source_location": "L18", "weight": 1.0}, {"source": "d_my_head_folders_my_desktop_agentic_loop_graph_tmp_mem0_server_models_py", "target": "server_models_apikey", "relation": "contains", "confidence": "EXTRACTED", "source_file": ".tmp_mem0/server/models.py", "source_location": "L30", "weight": 1.0}, {"source": "server_models_apikey", "target": "base", "relation": "inherits", "confidence": "EXTRACTED", "source_file": ".tmp_mem0/server/models.py", "source_location": "L30", "weight": 1.0}, {"source": "d_my_head_folders_my_desktop_agentic_loop_graph_tmp_mem0_server_models_py", "target": "server_models_requestlog", "relation": "contains", "confidence": "EXTRACTED", "source_file": ".tmp_mem0/server/models.py", "source_location": "L43", "weight": 1.0}, {"source": "server_models_requestlog", "target": "base", "relation": "inherits", "confidence": "EXTRACTED", "source_file": ".tmp_mem0/server/models.py", "source_location": "L43", "weight": 1.0}, {"source": "d_my_head_folders_my_desktop_agentic_loop_graph_tmp_mem0_server_models_py", "target": "server_models_refreshtokenjti", "relation": "contains", "confidence": "EXTRACTED", "source_file": ".tmp_mem0/server/models.py", "source_location": "L55", "weight": 1.0}, {"source": "server_models_refreshtokenjti", "target": "base", "relation": "inherits", "confidence": "EXTRACTED", "source_file": ".tmp_mem0/server/models.py", "source_location": "L55", "weight": 1.0}, {"source": "d_my_head_folders_my_desktop_agentic_loop_graph_tmp_mem0_server_models_py", "target": "server_models_settings", "relation": "contains", "confidence": "EXTRACTED", "source_file": ".tmp_mem0/server/models.py", "source_location": "L65", "weight": 1.0}, {"source": "server_models_settings", "target": "base", "relation": "inherits", "confidence": "EXTRACTED", "source_file": ".tmp_mem0/server/models.py", "source_location": "L65", "weight": 1.0}], "raw_calls": [{"caller_nid": "server_models_utcnow", "callee": "now", "is_member_call": true, "source_file": "D:\\My_head_folders\\My-desktop\\Agentic_Loop_Graph\\.tmp_mem0\\server\\models.py", "source_location": "L11", "receiver": null}, {"caller_nid": "server_models_new_uuid", "callee": "uuid4", "is_member_call": true, "source_file": "D:\\My_head_folders\\My-desktop\\Agentic_Loop_Graph\\.tmp_mem0\\server\\models.py", "source_location": "L15", "receiver": null}]}