{"nodes": [{"id": "d_my_head_folders_my_desktop_agentic_loop_graph_tmp_memanto_memanto_app_models_session_py", "label": "session.py", "file_type": "code", "source_file": ".tmp_memanto/memanto/app/models/session.py", "source_location": "L1"}, {"id": "models_session_sessionstatus", "label": "SessionStatus", "file_type": "code", "source_file": ".tmp_memanto/memanto/app/models/session.py", "source_location": "L17"}, {"id": "str", "label": "str", "file_type": "code", "source_file": "", "source_location": ""}, {"id": "enum", "label": "Enum", "file_type": "code", "source_file": "", "source_location": ""}, {"id": "models_session_agentpattern", "label": "AgentPattern", "file_type": "code", "source_file": ".tmp_memanto/memanto/app/models/session.py", "source_location": "L25"}, {"id": "models_session_sessioncreate", "label": "SessionCreate", "file_type": "code", "source_file": ".tmp_memanto/memanto/app/models/session.py", "source_location": "L33"}, {"id": "basemodel", "label": "BaseModel", "file_type": "code", "source_file": "", "source_location": ""}, {"id": "models_session_sessiontoken", "label": "SessionToken", "file_type": "code", "source_file": ".tmp_memanto/memanto/app/models/session.py", "source_location": "L43"}, {"id": "models_session_session", "label": "Session", "file_type": "code", "source_file": ".tmp_memanto/memanto/app/models/session.py", "source_location": "L53"}, {"id": "models_session_session_is_expired", "label": ".is_expired()", "file_type": "code", "source_file": ".tmp_memanto/memanto/app/models/session.py", "source_location": "L66"}, {"id": "models_session_session_is_active", "label": ".is_active()", "file_type": "code", "source_file": ".tmp_memanto/memanto/app/models/session.py", "source_location": "L70"}, {"id": "models_session_session_time_remaining", "label": ".time_remaining()", "file_type": "code", "source_file": ".tmp_memanto/memanto/app/models/session.py", "source_location": "L74"}, {"id": "timedelta", "label": "timedelta", "file_type": "code", "source_file": ".tmp_memanto/memanto/app/models/session.py", "source_location": "L74"}, {"id": "models_session_sessioninfo", "label": "SessionInfo", "file_type": "code", "source_file": ".tmp_memanto/memanto/app/models/session.py", "source_location": "L79"}, {"id": "models_session_sessionsummary", "label": "SessionSummary", "file_type": "code", "source_file": ".tmp_memanto/memanto/app/models/session.py", "source_location": "L92"}, {"id": "models_session_agentcreate", "label": "AgentCreate", "file_type": "code", "source_file": ".tmp_memanto/memanto/app/models/session.py", "source_location": "L104"}, {"id": "models_session_agentinfo", "label": "AgentInfo", "file_type": "code", "source_file": ".tmp_memanto/memanto/app/models/session.py", "source_location": "L121"}, {"id": "models_session_agentlist", "label": "AgentList", "file_type": "code", "source_file": ".tmp_memanto/memanto/app/models/session.py", "source_location": "L135"}, {"id": "models_session_rationale_1", "label": "Session Models for MEMANTO  Defines session-based authentication models for the", "file_type": "rationale", "source_file": ".tmp_memanto/memanto/app/models/session.py", "source_location": "L1"}, {"id": "models_session_rationale_26", "label": "Agent pattern types for memory organization", "file_type": "rationale", "source_file": ".tmp_memanto/memanto/app/models/session.py", "source_location": "L26"}, {"id": "models_session_rationale_34", "label": "Request to create/activate a session", "file_type": "rationale", "source_file": ".tmp_memanto/memanto/app/models/session.py", "source_location": "L34"}, {"id": "models_session_rationale_44", "label": "JWT token payload structure", "file_type": "rationale", "source_file": ".tmp_memanto/memanto/app/models/session.py", "source_location": "L44"}, {"id": "models_session_rationale_54", "label": "Active session information", "file_type": "rationale", "source_file": ".tmp_memanto/memanto/app/models/session.py", "source_location": "L54"}, {"id": "models_session_rationale_67", "label": "Check if session is expired", "file_type": "rationale", "source_file": ".tmp_memanto/memanto/app/models/session.py", "source_location": "L67"}, {"id": "models_session_rationale_71", "label": "Check if session is active", "file_type": "rationale", "source_file": ".tmp_memanto/memanto/app/models/session.py", "source_location": "L71"}, {"id": "models_session_rationale_75", "label": "Get time remaining in session", "file_type": "rationale", "source_file": ".tmp_memanto/memanto/app/models/session.py", "source_location": "L75"}, {"id": "models_session_rationale_80", "label": "Session information response", "file_type": "rationale", "source_file": ".tmp_memanto/memanto/app/models/session.py", "source_location": "L80"}, {"id": "models_session_rationale_93", "label": "Summary of ended session", "file_type": "rationale", "source_file": ".tmp_memanto/memanto/app/models/session.py", "source_location": "L93"}, {"id": "models_session_rationale_105", "label": "Request to create a new agent", "file_type": "rationale", "source_file": ".tmp_memanto/memanto/app/models/session.py", "source_location": "L105"}], "edges": [{"source": "d_my_head_folders_my_desktop_agentic_loop_graph_tmp_memanto_memanto_app_models_session_py", "target": "datetime", "relation": "imports_from", "context": "import", "confidence": "EXTRACTED", "source_file": ".tmp_memanto/memanto/app/models/session.py", "source_location": "L8", "weight": 1.0}, {"source": "d_my_head_folders_my_desktop_agentic_loop_graph_tmp_memanto_memanto_app_models_session_py", "target": "enum", "relation": "imports_from", "context": "import", "confidence": "EXTRACTED", "source_file": ".tmp_memanto/memanto/app/models/session.py", "source_location": "L9", "weight": 1.0}, {"source": "d_my_head_folders_my_desktop_agentic_loop_graph_tmp_memanto_memanto_app_models_session_py", "target": "typing", "relation": "imports_from", "context": "import", "confidence": "EXTRACTED", "source_file": ".tmp_memanto/memanto/app/models/session.py", "source_location": "L10", "weight": 1.0}, {"source": "d_my_head_folders_my_desktop_agentic_loop_graph_tmp_memanto_memanto_app_models_session_py", "target": "pydantic", "relation": "imports_from", "context": "import", "confidence": "EXTRACTED", "source_file": ".tmp_memanto/memanto/app/models/session.py", "source_location": "L12", "weight": 1.0}, {"source": "d_my_head_folders_my_desktop_agentic_loop_graph_tmp_memanto_memanto_app_models_session_py", "target": "memanto_app_utils_temporal_helpers", "relation": "imports_from", "context": "import", "confidence": "EXTRACTED", "source_file": ".tmp_memanto/memanto/app/models/session.py", "source_location": "L14", "weight": 1.0}, {"source": "d_my_head_folders_my_desktop_agentic_loop_graph_tmp_memanto_memanto_app_models_session_py", "target": "models_session_sessionstatus", "relation": "contains", "confidence": "EXTRACTED", "source_file": ".tmp_memanto/memanto/app/models/session.py", "source_location": "L17", "weight": 1.0}, {"source": "models_session_sessionstatus", "target": "str", "relation": "inherits", "confidence": "EXTRACTED", "source_file": ".tmp_memanto/memanto/app/models/session.py", "source_location": "L17", "weight": 1.0}, {"source": "models_session_sessionstatus", "target": "enum", "relation": "inherits", "confidence": "EXTRACTED", "source_file": ".tmp_memanto/memanto/app/models/session.py", "source_location": "L17", "weight": 1.0}, {"source": "d_my_head_folders_my_desktop_agentic_loop_graph_tmp_memanto_memanto_app_models_session_py", "target": "models_session_agentpattern", "relation": "contains", "confidence": "EXTRACTED", "source_file": ".tmp_memanto/memanto/app/models/session.py", "source_location": "L25", "weight": 1.0}, {"source": "models_session_agentpattern", "target": "str", "relation": "inherits", "confidence": "EXTRACTED", "source_file": ".tmp_memanto/memanto/app/models/session.py", "source_location": "L25", "weight": 1.0}, {"source": "models_session_agentpattern", "target": "enum", "relation": "inherits", "confidence": "EXTRACTED", "source_file": ".tmp_memanto/memanto/app/models/session.py", "source_location": "L25", "weight": 1.0}, {"source": "d_my_head_folders_my_desktop_agentic_loop_graph_tmp_memanto_memanto_app_models_session_py", "target": "models_session_sessioncreate", "relation": "contains", "confidence": "EXTRACTED", "source_file": ".tmp_memanto/memanto/app/models/session.py", "source_location": "L33", "weight": 1.0}, {"source": "models_session_sessioncreate", "target": "basemodel", "relation": "inherits", "confidence": "EXTRACTED", "source_file": ".tmp_memanto/memanto/app/models/session.py", "source_location": "L33", "weight": 1.0}, {"source": "d_my_head_folders_my_desktop_agentic_loop_graph_tmp_memanto_memanto_app_models_session_py", "target": "models_session_sessiontoken", "relation": "contains", "confidence": "EXTRACTED", "source_file": ".tmp_memanto/memanto/app/models/session.py", "source_location": "L43", "weight": 1.0}, {"source": "models_session_sessiontoken", "target": "basemodel", "relation": "inherits", "confidence": "EXTRACTED", "source_file": ".tmp_memanto/memanto/app/models/session.py", "source_location": "L43", "weight": 1.0}, {"source": "d_my_head_folders_my_desktop_agentic_loop_graph_tmp_memanto_memanto_app_models_session_py", "target": "models_session_session", "relation": "contains", "confidence": "EXTRACTED", "source_file": ".tmp_memanto/memanto/app/models/session.py", "source_location": "L53", "weight": 1.0}, {"source": "models_session_session", "target": "basemodel", "relation": "inherits", "confidence": "EXTRACTED", "source_file": ".tmp_memanto/memanto/app/models/session.py", "source_location": "L53", "weight": 1.0}, {"source": "models_session_session", "target": "models_session_session_is_expired", "relation": "method", "confidence": "EXTRACTED", "source_file": ".tmp_memanto/memanto/app/models/session.py", "source_location": "L66", "weight": 1.0}, {"source": "models_session_session", "target": "models_session_session_is_active", "relation": "method", "confidence": "EXTRACTED", "source_file": ".tmp_memanto/memanto/app/models/session.py", "source_location": "L70", "weight": 1.0}, {"source": "models_session_session", "target": "models_session_session_time_remaining", "relation": "method", "confidence": "EXTRACTED", "source_file": ".tmp_memanto/memanto/app/models/session.py", "source_location": "L74", "weight": 1.0}, {"source": "models_session_session_time_remaining", "target": "timedelta", "relation": "references", "context": "return_type", "confidence": "EXTRACTED", "source_file": ".tmp_memanto/memanto/app/models/session.py", "source_location": "L74", "weight": 1.0}, {"source": "d_my_head_folders_my_desktop_agentic_loop_graph_tmp_memanto_memanto_app_models_session_py", "target": "models_session_sessioninfo", "relation": "contains", "confidence": "EXTRACTED", "source_file": ".tmp_memanto/memanto/app/models/session.py", "source_location": "L79", "weight": 1.0}, {"source": "models_session_sessioninfo", "target": "basemodel", "relation": "inherits", "confidence": "EXTRACTED", "source_file": ".tmp_memanto/memanto/app/models/session.py", "source_location": "L79", "weight": 1.0}, {"source": "d_my_head_folders_my_desktop_agentic_loop_graph_tmp_memanto_memanto_app_models_session_py", "target": "models_session_sessionsummary", "relation": "contains", "confidence": "EXTRACTED", "source_file": ".tmp_memanto/memanto/app/models/session.py", "source_location": "L92", "weight": 1.0}, {"source": "models_session_sessionsummary", "target": "basemodel", "relation": "inherits", "confidence": "EXTRACTED", "source_file": ".tmp_memanto/memanto/app/models/session.py", "source_location": "L92", "weight": 1.0}, {"source": "d_my_head_folders_my_desktop_agentic_loop_graph_tmp_memanto_memanto_app_models_session_py", "target": "models_session_agentcreate", "relation": "contains", "confidence": "EXTRACTED", "source_file": ".tmp_memanto/memanto/app/models/session.py", "source_location": "L104", "weight": 1.0}, {"source": "models_session_agentcreate", "target": "basemodel", "relation": "inherits", "confidence": "EXTRACTED", "source_file": ".tmp_memanto/memanto/app/models/session.py", "source_location": "L104", "weight": 1.0}, {"source": "d_my_head_folders_my_desktop_agentic_loop_graph_tmp_memanto_memanto_app_models_session_py", "target": "models_session_agentinfo", "relation": "contains", "confidence": "EXTRACTED", "source_file": ".tmp_memanto/memanto/app/models/session.py", "source_location": "L121", "weight": 1.0}, {"source": "models_session_agentinfo", "target": "basemodel", "relation": "inherits", "confidence": "EXTRACTED", "source_file": ".tmp_memanto/memanto/app/models/session.py", "source_location": "L121", "weight": 1.0}, {"source": "d_my_head_folders_my_desktop_agentic_loop_graph_tmp_memanto_memanto_app_models_session_py", "target": "models_session_agentlist", "relation": "contains", "confidence": "EXTRACTED", "source_file": ".tmp_memanto/memanto/app/models/session.py", "source_location": "L135", "weight": 1.0}, {"source": "models_session_agentlist", "target": "basemodel", "relation": "inherits", "confidence": "EXTRACTED", "source_file": ".tmp_memanto/memanto/app/models/session.py", "source_location": "L135", "weight": 1.0}, {"source": "models_session_session_is_active", "target": "models_session_session_is_expired", "relation": "calls", "context": "call", "confidence": "EXTRACTED", "source_file": ".tmp_memanto/memanto/app/models/session.py", "source_location": "L72", "weight": 1.0}, {"source": "models_session_rationale_1", "target": "d_my_head_folders_my_desktop_agentic_loop_graph_tmp_memanto_memanto_app_models_session_py", "relation": "rationale_for", "confidence": "EXTRACTED", "source_file": ".tmp_memanto/memanto/app/models/session.py", "source_location": "L1", "weight": 1.0}, {"source": "models_session_rationale_26", "target": "models_session_agentpattern", "relation": "rationale_for", "confidence": "EXTRACTED", "source_file": ".tmp_memanto/memanto/app/models/session.py", "source_location": "L26", "weight": 1.0}, {"source": "models_session_rationale_34", "target": "models_session_sessioncreate", "relation": "rationale_for", "confidence": "EXTRACTED", "source_file": ".tmp_memanto/memanto/app/models/session.py", "source_location": "L34", "weight": 1.0}, {"source": "models_session_rationale_44", "target": "models_session_sessiontoken", "relation": "rationale_for", "confidence": "EXTRACTED", "source_file": ".tmp_memanto/memanto/app/models/session.py", "source_location": "L44", "weight": 1.0}, {"source": "models_session_rationale_54", "target": "models_session_session", "relation": "rationale_for", "confidence": "EXTRACTED", "source_file": ".tmp_memanto/memanto/app/models/session.py", "source_location": "L54", "weight": 1.0}, {"source": "models_session_rationale_67", "target": "models_session_session_is_expired", "relation": "rationale_for", "confidence": "EXTRACTED", "source_file": ".tmp_memanto/memanto/app/models/session.py", "source_location": "L67", "weight": 1.0}, {"source": "models_session_rationale_71", "target": "models_session_session_is_active", "relation": "rationale_for", "confidence": "EXTRACTED", "source_file": ".tmp_memanto/memanto/app/models/session.py", "source_location": "L71", "weight": 1.0}, {"source": "models_session_rationale_75", "target": "models_session_session_time_remaining", "relation": "rationale_for", "confidence": "EXTRACTED", "source_file": ".tmp_memanto/memanto/app/models/session.py", "source_location": "L75", "weight": 1.0}, {"source": "models_session_rationale_80", "target": "models_session_sessioninfo", "relation": "rationale_for", "confidence": "EXTRACTED", "source_file": ".tmp_memanto/memanto/app/models/session.py", "source_location": "L80", "weight": 1.0}, {"source": "models_session_rationale_93", "target": "models_session_sessionsummary", "relation": "rationale_for", "confidence": "EXTRACTED", "source_file": ".tmp_memanto/memanto/app/models/session.py", "source_location": "L93", "weight": 1.0}, {"source": "models_session_rationale_105", "target": "models_session_agentcreate", "relation": "rationale_for", "confidence": "EXTRACTED", "source_file": ".tmp_memanto/memanto/app/models/session.py", "source_location": "L105", "weight": 1.0}], "raw_calls": [{"caller_nid": "models_session_session_is_expired", "callee": "utc_now", "is_member_call": false, "source_file": "D:\\My_head_folders\\My-desktop\\Agentic_Loop_Graph\\.tmp_memanto\\memanto\\app\\models\\session.py", "source_location": "L68", "receiver": null}, {"caller_nid": "models_session_session_time_remaining", "callee": "utc_now", "is_member_call": false, "source_file": "D:\\My_head_folders\\My-desktop\\Agentic_Loop_Graph\\.tmp_memanto\\memanto\\app\\models\\session.py", "source_location": "L76", "receiver": null}]}