{"nodes": [{"id": "d_my_head_folders_my_desktop_agentic_loop_graph_figma_agent_core_readme_md", "label": "README.md", "file_type": "document", "source_file": "figma-agent-core/README.md", "source_location": "L1"}, {"id": "figma_agent_core_readme_figma_agent_core", "label": "Figma Agent Core", "file_type": "document", "source_file": "figma-agent-core/README.md", "source_location": "L1"}, {"id": "figma_agent_core_readme_\u0431\u044b\u0441\u0442\u0440\u044b\u0439_\u0441\u0442\u0430\u0440\u0442", "label": "\u0411\u044b\u0441\u0442\u0440\u044b\u0439 \u0441\u0442\u0430\u0440\u0442", "file_type": "document", "source_file": "figma-agent-core/README.md", "source_location": "L5"}, {"id": "figma_agent_core_readme_1_\u0443\u0441\u0442\u0430\u043d\u043e\u0432\u043a\u0430_\u0437\u0430\u0432\u0438\u0441\u0438\u043c\u043e\u0441\u0442\u0435\u0439", "label": "1. \u0423\u0441\u0442\u0430\u043d\u043e\u0432\u043a\u0430 \u0437\u0430\u0432\u0438\u0441\u0438\u043c\u043e\u0441\u0442\u0435\u0439", "file_type": "document", "source_file": "figma-agent-core/README.md", "source_location": "L7"}, {"id": "figma_agent_core_readme_2_\u043d\u0430\u0441\u0442\u0440\u043e\u0439\u043a\u0430_\u043e\u043a\u0440\u0443\u0436\u0435\u043d\u0438\u044f", "label": "2. \u041d\u0430\u0441\u0442\u0440\u043e\u0439\u043a\u0430 \u043e\u043a\u0440\u0443\u0436\u0435\u043d\u0438\u044f", "file_type": "document", "source_file": "figma-agent-core/README.md", "source_location": "L13"}, {"id": "figma_agent_core_readme_3_\u0437\u0430\u043f\u0443\u0441\u043a_\u043f\u043e\u043b\u043d\u043e\u0433\u043e_\u043f\u0430\u0439\u043f\u043b\u0430\u0439\u043d\u0430", "label": "3. \u0417\u0430\u043f\u0443\u0441\u043a \u043f\u043e\u043b\u043d\u043e\u0433\u043e \u043f\u0430\u0439\u043f\u043b\u0430\u0439\u043d\u0430", "file_type": "document", "source_file": "figma-agent-core/README.md", "source_location": "L27"}, {"id": "figma_agent_core_readme_\u0440\u0430\u0431\u043e\u0442\u0430_\u0441_\u043a\u043e\u043d\u043a\u0440\u0435\u0442\u043d\u043e\u0439_\u0441\u0435\u043a\u0446\u0438\u0435\u0439", "label": "\u0420\u0430\u0431\u043e\u0442\u0430 \u0441 \u043a\u043e\u043d\u043a\u0440\u0435\u0442\u043d\u043e\u0439 \u0441\u0435\u043a\u0446\u0438\u0435\u0439", "file_type": "document", "source_file": "figma-agent-core/README.md", "source_location": "L49"}, {"id": "figma_agent_core_readme_\u0441\u0435\u043c\u0430\u043d\u0442\u0438\u0447\u0435\u0441\u043a\u043e\u0435_\u0441\u0436\u0430\u0442\u0438\u0435_\u043a\u043e\u043d\u0442\u0435\u043a\u0441\u0442\u0430", "label": "\u0421\u0435\u043c\u0430\u043d\u0442\u0438\u0447\u0435\u0441\u043a\u043e\u0435 \u0441\u0436\u0430\u0442\u0438\u0435 \u043a\u043e\u043d\u0442\u0435\u043a\u0441\u0442\u0430", "file_type": "document", "source_file": "figma-agent-core/README.md", "source_location": "L72"}, {"id": "figma_agent_core_readme_\u0434\u0438\u0437\u0430\u0439\u043d_\u0442\u043e\u043a\u0435\u043d\u044b_\u0438_\u0430\u0441\u0441\u0435\u0442\u044b", "label": "\u0414\u0438\u0437\u0430\u0439\u043d-\u0442\u043e\u043a\u0435\u043d\u044b \u0438 \u0430\u0441\u0441\u0435\u0442\u044b", "file_type": "document", "source_file": "figma-agent-core/README.md", "source_location": "L89"}, {"id": "figma_agent_core_readme_\u0441\u0442\u0440\u0443\u043a\u0442\u0443\u0440\u0430_\u043f\u0440\u043e\u0435\u043a\u0442\u0430", "label": "\u0421\u0442\u0440\u0443\u043a\u0442\u0443\u0440\u0430 \u043f\u0440\u043e\u0435\u043a\u0442\u0430", "file_type": "document", "source_file": "figma-agent-core/README.md", "source_location": "L112"}, {"id": "figma_agent_core_readme_\u0442\u0440\u0435\u0431\u043e\u0432\u0430\u043d\u0438\u044f", "label": "\u0422\u0440\u0435\u0431\u043e\u0432\u0430\u043d\u0438\u044f", "file_type": "document", "source_file": "figma-agent-core/README.md", "source_location": "L124"}, {"id": "figma_agent_core_readme_\u0431\u0435\u0437\u043e\u043f\u0430\u0441\u043d\u043e\u0441\u0442\u044c", "label": "\u0411\u0435\u0437\u043e\u043f\u0430\u0441\u043d\u043e\u0441\u0442\u044c", "file_type": "document", "source_file": "figma-agent-core/README.md", "source_location": "L131"}], "edges": [{"source": "d_my_head_folders_my_desktop_agentic_loop_graph_figma_agent_core_readme_md", "target": "figma_agent_core_readme_figma_agent_core", "relation": "contains", "confidence": "EXTRACTED", "source_file": "figma-agent-core/README.md", "source_location": "L1", "weight": 1.0}, {"source": "figma_agent_core_readme_figma_agent_core", "target": "figma_agent_core_readme_\u0431\u044b\u0441\u0442\u0440\u044b\u0439_\u0441\u0442\u0430\u0440\u0442", "relation": "contains", "confidence": "EXTRACTED", "source_file": "figma-agent-core/README.md", "source_location": "L5", "weight": 1.0}, {"source": "figma_agent_core_readme_\u0431\u044b\u0441\u0442\u0440\u044b\u0439_\u0441\u0442\u0430\u0440\u0442", "target": "figma_agent_core_readme_1_\u0443\u0441\u0442\u0430\u043d\u043e\u0432\u043a\u0430_\u0437\u0430\u0432\u0438\u0441\u0438\u043c\u043e\u0441\u0442\u0435\u0439", "relation": "contains", "confidence": "EXTRACTED", "source_file": "figma-agent-core/README.md", "source_location": "L7", "weight": 1.0}, {"source": "figma_agent_core_readme_\u0431\u044b\u0441\u0442\u0440\u044b\u0439_\u0441\u0442\u0430\u0440\u0442", "target": "figma_agent_core_readme_2_\u043d\u0430\u0441\u0442\u0440\u043e\u0439\u043a\u0430_\u043e\u043a\u0440\u0443\u0436\u0435\u043d\u0438\u044f", "relation": "contains", "confidence": "EXTRACTED", "source_file": "figma-agent-core/README.md", "source_location": "L13", "weight": 1.0}, {"source": "figma_agent_core_readme_\u0431\u044b\u0441\u0442\u0440\u044b\u0439_\u0441\u0442\u0430\u0440\u0442", "target": "figma_agent_core_readme_3_\u0437\u0430\u043f\u0443\u0441\u043a_\u043f\u043e\u043b\u043d\u043e\u0433\u043e_\u043f\u0430\u0439\u043f\u043b\u0430\u0439\u043d\u0430", "relation": "contains", "confidence": "EXTRACTED", "source_file": "figma-agent-core/README.md", "source_location": "L27", "weight": 1.0}, {"source": "figma_agent_core_readme_\u0431\u044b\u0441\u0442\u0440\u044b\u0439_\u0441\u0442\u0430\u0440\u0442", "target": "figma_agent_core_readme_\u0440\u0430\u0431\u043e\u0442\u0430_\u0441_\u043a\u043e\u043d\u043a\u0440\u0435\u0442\u043d\u043e\u0439_\u0441\u0435\u043a\u0446\u0438\u0435\u0439", "relation": "contains", "confidence": "EXTRACTED", "source_file": "figma-agent-core/README.md", "source_location": "L49", "weight": 1.0}, {"source": "figma_agent_core_readme_figma_agent_core", "target": "figma_agent_core_readme_\u0441\u0435\u043c\u0430\u043d\u0442\u0438\u0447\u0435\u0441\u043a\u043e\u0435_\u0441\u0436\u0430\u0442\u0438\u0435_\u043a\u043e\u043d\u0442\u0435\u043a\u0441\u0442\u0430", "relation": "contains", "confidence": "EXTRACTED", "source_file": "figma-agent-core/README.md", "source_location": "L72", "weight": 1.0}, {"source": "figma_agent_core_readme_figma_agent_core", "target": "figma_agent_core_readme_\u0434\u0438\u0437\u0430\u0439\u043d_\u0442\u043e\u043a\u0435\u043d\u044b_\u0438_\u0430\u0441\u0441\u0435\u0442\u044b", "relation": "contains", "confidence": "EXTRACTED", "source_file": "figma-agent-core/README.md", "source_location": "L89", "weight": 1.0}, {"source": "figma_agent_core_readme_figma_agent_core", "target": "figma_agent_core_readme_\u0441\u0442\u0440\u0443\u043a\u0442\u0443\u0440\u0430_\u043f\u0440\u043e\u0435\u043a\u0442\u0430", "relation": "contains", "confidence": "EXTRACTED", "source_file": "figma-agent-core/README.md", "source_location": "L112", "weight": 1.0}, {"source": "figma_agent_core_readme_figma_agent_core", "target": "figma_agent_core_readme_\u0442\u0440\u0435\u0431\u043e\u0432\u0430\u043d\u0438\u044f", "relation": "contains", "confidence": "EXTRACTED", "source_file": "figma-agent-core/README.md", "source_location": "L124", "weight": 1.0}, {"source": "figma_agent_core_readme_figma_agent_core", "target": "figma_agent_core_readme_\u0431\u0435\u0437\u043e\u043f\u0430\u0441\u043d\u043e\u0441\u0442\u044c", "relation": "contains", "confidence": "EXTRACTED", "source_file": "figma-agent-core/README.md", "source_location": "L131", "weight": 1.0}], "input_tokens": 0, "output_tokens": 0}